{"config":{"theme":"health","industryPool":["Medical Devices","Pharmaceuticals","Health IT","Biotech","Digital Health","Diagnostics","Hospital Systems"],"titlePool":["Chief Medical Officer","Director of Nursing","Clinical Research Lead","Hospital Administrator","VP Regulatory","Biomedical Engineer","Physician","Head of R&D"],"sessionTopics":["AI in Diagnostics","Value-Based Care","FDA Pathways","Interoperability & FHIR","Remote Patient Monitoring","Clinical Trial Design"],"id":"healthit-summit-2026","order":9,"eventName":"HealthIT Summit 2026","tagline":"Interoperability and the connected patient","venue":"Gaylord National Resort","city":"National Harbor","country":"United States","dates":{"start":"2026-02-24","end":"2026-02-25"},"seed":202,"difficulty":"easy","layout":"card-grid","surface":"ssr","label":"Health · easy · SSR · 120p · full fields","scale":{"individuals":120,"companies":0,"sessions":0},"coverage":{"entities":["individuals"],"emailsInline":true,"fieldFullness":"full"}},"counts":{"individuals":120,"companies":0,"events":0}}